cryptos/__init__.py
cryptos/blocks.py
cryptos/composite.py
cryptos/deterministic.py
cryptos/english.txt
cryptos/main.py
cryptos/mnemonic.py
cryptos/py2specials.py
cryptos/py3specials.py
cryptos/ripemd.py
cryptos/stealth.py
cryptos/transaction.py
cryptos/coins/__init__.py
cryptos/coins/base.py
cryptos/coins/bitcoin.py
cryptos/coins/bitcoin_cash.py
cryptos/coins/dash.py
cryptos/coins/dogecoin.py
cryptos/coins/litecoin.py
cryptos/explorers/__init__.py
cryptos/explorers/base_insight.py
cryptos/explorers/bitpay.py
cryptos/explorers/blockchain.py
cryptos/explorers/blockcypher.py
cryptos/explorers/blockdozer.py
cryptos/explorers/btg_explorer.py
cryptos/explorers/dash_siampm.py
cryptos/explorers/sochain.py
cryptos/explorers/utils.py
cryptos-1.36.data/scripts/cryptotool
cryptos-1.36.dist-info/DESCRIPTION.rst
cryptos-1.36.dist-info/METADATA
cryptos-1.36.dist-info/RECORD
cryptos-1.36.dist-info/WHEEL
cryptos-1.36.dist-info/metadata.json
cryptos-1.36.dist-info/top_level.txt
