Metadata-Version: 1.1
Name: cryptos
Version: 1.36
Summary: Python Crypto Coin Tools
Home-page: http://github.com/primal100/pybitcointools
Author: Paul Martin
Author-email: paulmartinforwork@gmail.com
License: UNKNOWN
Platform: UNKNOWN
Classifier: Development Status :: 5 - Production/Stable
Classifier: Intended Audience :: Developers
Classifier: Intended Audience :: Education
Classifier: License :: OSI Approved :: MIT License
Classifier: Operating System :: OS Independent
Classifier: Programming Language :: Python
Classifier: Programming Language :: Python :: 2
Classifier: Programming Language :: Python :: 3
Classifier: Topic :: Security :: Cryptography
